[
  {
    "ContainingType": "WMS.API.Controllers.V1.AuthorizationController",
    "Method": "Login",
    "RelativePath": "api/v1/Authorization/login",
    "HttpMethod": "POST",
    "IsController": true,
    "Order": 0,
    "Parameters": [
      {
        "Name": "command",
        "Type": "WMS.Application.Features.Authorization.Commands.LoginCommand",
        "IsRequired": true
      }
    ],
    "ReturnTypes": [
      {
        "Type": "System.Object",
        "MediaTypes": [
          "text/plain",
          "application/json",
          "text/json"
        ],
        "StatusCode": 200
      },
      {
        "Type": "Microsoft.AspNetCore.Mvc.ProblemDetails",
        "MediaTypes": [
          "text/plain",
          "application/json",
          "text/json"
        ],
        "StatusCode": 400
      },
      {
        "Type": "Microsoft.AspNetCore.Mvc.ProblemDetails",
        "MediaTypes": [
          "text/plain",
          "application/json",
          "text/json"
        ],
        "StatusCode": 401
      },
      {
        "Type": "System.Void",
        "MediaTypes": [],
        "StatusCode": 500
      }
    ]
  },
  {
    "ContainingType": "WMS.API.Controllers.V1.AuthorizationController",
    "Method": "RegisterUser",
    "RelativePath": "api/v1/Authorization/register",
    "HttpMethod": "POST",
    "IsController": true,
    "Order": 0,
    "Parameters": [
      {
        "Name": "command",
        "Type": "WMS.Application.Features.Authorization.Commands.RegisterUserCommand",
        "IsRequired": true
      }
    ],
    "ReturnTypes": [
      {
        "Type": "System.Object",
        "MediaTypes": [
          "text/plain",
          "application/json",
          "text/json"
        ],
        "StatusCode": 201
      },
      {
        "Type": "Microsoft.AspNetCore.Mvc.ProblemDetails",
        "MediaTypes": [
          "text/plain",
          "application/json",
          "text/json"
        ],
        "StatusCode": 400
      },
      {
        "Type": "System.Void",
        "MediaTypes": [],
        "StatusCode": 500
      }
    ]
  },
  {
    "ContainingType": "WMS.API.Controllers.V1.CategoriesController",
    "Method": "CreateCategory",
    "RelativePath": "api/v1/Categories",
    "HttpMethod": "POST",
    "IsController": true,
    "Order": 0,
    "Parameters": [
      {
        "Name": "command",
        "Type": "WMS.Application.Features.Categories.Commands.CreateCategoryCommand",
        "IsRequired": true
      }
    ],
    "ReturnTypes": [
      {
        "Type": "System.Object",
        "MediaTypes": [
          "text/plain",
          "application/json",
          "text/json"
        ],
        "StatusCode": 201
      },
      {
        "Type": "Microsoft.AspNetCore.Mvc.ProblemDetails",
        "MediaTypes": [
          "text/plain",
          "application/json",
          "text/json"
        ],
        "StatusCode": 400
      },
      {
        "Type": "Microsoft.AspNetCore.Mvc.ProblemDetails",
        "MediaTypes": [
          "text/plain",
          "application/json",
          "text/json"
        ],
        "StatusCode": 401
      },
      {
        "Type": "Microsoft.AspNetCore.Mvc.ProblemDetails",
        "MediaTypes": [
          "text/plain",
          "application/json",
          "text/json"
        ],
        "StatusCode": 403
      },
      {
        "Type": "System.Void",
        "MediaTypes": [],
        "StatusCode": 500
      }
    ]
  },
  {
    "ContainingType": "WMS.API.Controllers.V1.CategoriesController",
    "Method": "ListCategories",
    "RelativePath": "api/v1/Categories",
    "HttpMethod": "GET",
    "IsController": true,
    "Order": 0,
    "Parameters": [
      {
        "Name": "SearchTerm",
        "Type": "System.String",
        "IsRequired": false
      },
      {
        "Name": "PageNumber",
        "Type": "System.Int32",
        "IsRequired": false
      },
      {
        "Name": "PageSize",
        "Type": "System.Int32",
        "IsRequired": false
      }
    ],
    "ReturnTypes": [
      {
        "Type": "WMS.Application.Common.Models.PagedResult\u00601[[WMS.Application.Features.Categories.Queries.CategoryDto, WMS.Application, Version=1.0.0.0, Culture=neutral, PublicKeyToken=null]]",
        "MediaTypes": [
          "text/plain",
          "application/json",
          "text/json"
        ],
        "StatusCode": 200
      },
      {
        "Type": "Microsoft.AspNetCore.Mvc.ProblemDetails",
        "MediaTypes": [
          "text/plain",
          "application/json",
          "text/json"
        ],
        "StatusCode": 400
      },
      {
        "Type": "Microsoft.AspNetCore.Mvc.ProblemDetails",
        "MediaTypes": [
          "text/plain",
          "application/json",
          "text/json"
        ],
        "StatusCode": 401
      },
      {
        "Type": "Microsoft.AspNetCore.Mvc.ProblemDetails",
        "MediaTypes": [
          "text/plain",
          "application/json",
          "text/json"
        ],
        "StatusCode": 403
      },
      {
        "Type": "System.Void",
        "MediaTypes": [],
        "StatusCode": 500
      }
    ]
  },
  {
    "ContainingType": "WMS.API.Controllers.V1.CategoriesController",
    "Method": "GetCategoryTree",
    "RelativePath": "api/v1/Categories/tree",
    "HttpMethod": "GET",
    "IsController": true,
    "Order": 0,
    "Parameters": [
      {
        "Name": "query",
        "Type": "WMS.Application.Features.Categories.Queries.GetCategoryTreeQuery",
        "IsRequired": false
      }
    ],
    "ReturnTypes": [
      {
        "Type": "System.Collections.Generic.List\u00601[[WMS.Application.Features.Categories.Queries.CategoryTreeDto, WMS.Application, Version=1.0.0.0, Culture=neutral, PublicKeyToken=null]]",
        "MediaTypes": [
          "text/plain",
          "application/json",
          "text/json"
        ],
        "StatusCode": 200
      },
      {
        "Type": "Microsoft.AspNetCore.Mvc.ProblemDetails",
        "MediaTypes": [
          "text/plain",
          "application/json",
          "text/json"
        ],
        "StatusCode": 400
      },
      {
        "Type": "Microsoft.AspNetCore.Mvc.ProblemDetails",
        "MediaTypes": [
          "text/plain",
          "application/json",
          "text/json"
        ],
        "StatusCode": 401
      },
      {
        "Type": "Microsoft.AspNetCore.Mvc.ProblemDetails",
        "MediaTypes": [
          "text/plain",
          "application/json",
          "text/json"
        ],
        "StatusCode": 403
      },
      {
        "Type": "System.Void",
        "MediaTypes": [],
        "StatusCode": 500
      }
    ]
  },
  {
    "ContainingType": "WMS.API.Controllers.V1.LocationsController",
    "Method": "CreateLocation",
    "RelativePath": "api/v1/Locations",
    "HttpMethod": "POST",
    "IsController": true,
    "Order": 0,
    "Parameters": [
      {
        "Name": "command",
        "Type": "WMS.Application.Features.Locations.Commands.CreateLocationCommand",
        "IsRequired": true
      }
    ],
    "ReturnTypes": [
      {
        "Type": "System.Object",
        "MediaTypes": [
          "text/plain",
          "application/json",
          "text/json"
        ],
        "StatusCode": 201
      },
      {
        "Type": "Microsoft.AspNetCore.Mvc.ProblemDetails",
        "MediaTypes": [
          "text/plain",
          "application/json",
          "text/json"
        ],
        "StatusCode": 400
      },
      {
        "Type": "Microsoft.AspNetCore.Mvc.ProblemDetails",
        "MediaTypes": [
          "text/plain",
          "application/json",
          "text/json"
        ],
        "StatusCode": 401
      },
      {
        "Type": "Microsoft.AspNetCore.Mvc.ProblemDetails",
        "MediaTypes": [
          "text/plain",
          "application/json",
          "text/json"
        ],
        "StatusCode": 403
      },
      {
        "Type": "System.Void",
        "MediaTypes": [],
        "StatusCode": 500
      }
    ]
  },
  {
    "ContainingType": "WMS.API.Controllers.V1.LocationsController",
    "Method": "DeactivateLocation",
    "RelativePath": "api/v1/Locations/Deactivate/{id}",
    "HttpMethod": "POST",
    "IsController": true,
    "Order": 0,
    "Parameters": [
      {
        "Name": "id",
        "Type": "System.Int32",
        "IsRequired": true
      }
    ],
    "ReturnTypes": [
      {
        "Type": "System.Void",
        "MediaTypes": [],
        "StatusCode": 204
      },
      {
        "Type": "Microsoft.AspNetCore.Mvc.ProblemDetails",
        "MediaTypes": [
          "text/plain",
          "application/json",
          "text/json"
        ],
        "StatusCode": 400
      },
      {
        "Type": "Microsoft.AspNetCore.Mvc.ProblemDetails",
        "MediaTypes": [
          "text/plain",
          "application/json",
          "text/json"
        ],
        "StatusCode": 404
      },
      {
        "Type": "Microsoft.AspNetCore.Mvc.ProblemDetails",
        "MediaTypes": [
          "text/plain",
          "application/json",
          "text/json"
        ],
        "StatusCode": 409
      }
    ]
  },
  {
    "ContainingType": "WMS.API.Controllers.V1.LocationsController",
    "Method": "UpdateLocation",
    "RelativePath": "api/v1/Locations/Update/{id}",
    "HttpMethod": "PUT",
    "IsController": true,
    "Order": 0,
    "Parameters": [
      {
        "Name": "id",
        "Type": "System.Int32",
        "IsRequired": true
      },
      {
        "Name": "command",
        "Type": "WMS.Application.Features.Locations.Commands.UpdateLocationCommand",
        "IsRequired": true
      }
    ],
    "ReturnTypes": [
      {
        "Type": "System.Void",
        "MediaTypes": [],
        "StatusCode": 204
      },
      {
        "Type": "Microsoft.AspNetCore.Mvc.ProblemDetails",
        "MediaTypes": [
          "text/plain",
          "application/json",
          "text/json"
        ],
        "StatusCode": 400
      },
      {
        "Type": "Microsoft.AspNetCore.Mvc.ProblemDetails",
        "MediaTypes": [
          "text/plain",
          "application/json",
          "text/json"
        ],
        "StatusCode": 401
      },
      {
        "Type": "Microsoft.AspNetCore.Mvc.ProblemDetails",
        "MediaTypes": [
          "text/plain",
          "application/json",
          "text/json"
        ],
        "StatusCode": 403
      },
      {
        "Type": "Microsoft.AspNetCore.Mvc.ProblemDetails",
        "MediaTypes": [
          "text/plain",
          "application/json",
          "text/json"
        ],
        "StatusCode": 404
      }
    ]
  },
  {
    "ContainingType": "WMS.API.Controllers.V1.LocationsController",
    "Method": "GetLocationTree",
    "RelativePath": "api/v1/Locations/warehouse/{warehouseId}/tree",
    "HttpMethod": "GET",
    "IsController": true,
    "Order": 0,
    "Parameters": [
      {
        "Name": "warehouseId",
        "Type": "System.Int32",
        "IsRequired": true
      }
    ],
    "ReturnTypes": [
      {
        "Type": "System.Collections.Generic.List\u00601[[WMS.Application.Features.Locations.Queries.LocationTreeDto, WMS.Application, Version=1.0.0.0, Culture=neutral, PublicKeyToken=null]]",
        "MediaTypes": [
          "text/plain",
          "application/json",
          "text/json"
        ],
        "StatusCode": 200
      },
      {
        "Type": "Microsoft.AspNetCore.Mvc.ProblemDetails",
        "MediaTypes": [
          "text/plain",
          "application/json",
          "text/json"
        ],
        "StatusCode": 400
      },
      {
        "Type": "Microsoft.AspNetCore.Mvc.ProblemDetails",
        "MediaTypes": [
          "text/plain",
          "application/json",
          "text/json"
        ],
        "StatusCode": 401
      },
      {
        "Type": "Microsoft.AspNetCore.Mvc.ProblemDetails",
        "MediaTypes": [
          "text/plain",
          "application/json",
          "text/json"
        ],
        "StatusCode": 403
      },
      {
        "Type": "System.Void",
        "MediaTypes": [],
        "StatusCode": 500
      }
    ]
  },
  {
    "ContainingType": "WMS.API.Controllers.V1.ProductsController",
    "Method": "CreateProduct",
    "RelativePath": "api/v1/Products",
    "HttpMethod": "POST",
    "IsController": true,
    "Order": 0,
    "Parameters": [
      {
        "Name": "command",
        "Type": "WMS.Application.Features.Products.Commands.CreateProductCommand",
        "IsRequired": true
      }
    ],
    "ReturnTypes": [
      {
        "Type": "System.Object",
        "MediaTypes": [
          "text/plain",
          "application/json",
          "text/json"
        ],
        "StatusCode": 201
      },
      {
        "Type": "Microsoft.AspNetCore.Mvc.ProblemDetails",
        "MediaTypes": [
          "text/plain",
          "application/json",
          "text/json"
        ],
        "StatusCode": 400
      },
      {
        "Type": "Microsoft.AspNetCore.Mvc.ProblemDetails",
        "MediaTypes": [
          "text/plain",
          "application/json",
          "text/json"
        ],
        "StatusCode": 401
      },
      {
        "Type": "Microsoft.AspNetCore.Mvc.ProblemDetails",
        "MediaTypes": [
          "text/plain",
          "application/json",
          "text/json"
        ],
        "StatusCode": 403
      },
      {
        "Type": "System.Void",
        "MediaTypes": [],
        "StatusCode": 500
      }
    ]
  },
  {
    "ContainingType": "WMS.API.Controllers.V1.ProductsController",
    "Method": "ListProducts",
    "RelativePath": "api/v1/Products",
    "HttpMethod": "GET",
    "IsController": true,
    "Order": 0,
    "Parameters": [
      {
        "Name": "SearchTerm",
        "Type": "System.String",
        "IsRequired": false
      },
      {
        "Name": "CategoryId",
        "Type": "System.Nullable\u00601[[System.Int32, System.Private.CoreLib, Version=8.0.0.0, Culture=neutral, PublicKeyToken=7cec85d7bea7798e]]",
        "IsRequired": false
      },
      {
        "Name": "PageNumber",
        "Type": "System.Int32",
        "IsRequired": false
      },
      {
        "Name": "PageSize",
        "Type": "System.Int32",
        "IsRequired": false
      }
    ],
    "ReturnTypes": [
      {
        "Type": "WMS.Application.Common.Models.PagedResult\u00601[[WMS.Application.Features.Products.Queries.ProductDto, WMS.Application, Version=1.0.0.0, Culture=neutral, PublicKeyToken=null]]",
        "MediaTypes": [
          "text/plain",
          "application/json",
          "text/json"
        ],
        "StatusCode": 200
      },
      {
        "Type": "Microsoft.AspNetCore.Mvc.ProblemDetails",
        "MediaTypes": [
          "text/plain",
          "application/json",
          "text/json"
        ],
        "StatusCode": 400
      },
      {
        "Type": "Microsoft.AspNetCore.Mvc.ProblemDetails",
        "MediaTypes": [
          "text/plain",
          "application/json",
          "text/json"
        ],
        "StatusCode": 401
      },
      {
        "Type": "Microsoft.AspNetCore.Mvc.ProblemDetails",
        "MediaTypes": [
          "text/plain",
          "application/json",
          "text/json"
        ],
        "StatusCode": 403
      },
      {
        "Type": "System.Void",
        "MediaTypes": [],
        "StatusCode": 500
      }
    ]
  },
  {
    "ContainingType": "WMS.API.Controllers.V1.ProductsController",
    "Method": "AssignCategories",
    "RelativePath": "api/v1/Products/{id}/categories",
    "HttpMethod": "POST",
    "IsController": true,
    "Order": 0,
    "Parameters": [
      {
        "Name": "id",
        "Type": "System.Int32",
        "IsRequired": true
      },
      {
        "Name": "categoryIds",
        "Type": "System.Collections.Generic.List\u00601[[System.Int32, System.Private.CoreLib, Version=8.0.0.0, Culture=neutral, PublicKeyToken=7cec85d7bea7798e]]",
        "IsRequired": true
      }
    ],
    "ReturnTypes": [
      {
        "Type": "System.Void",
        "MediaTypes": [],
        "StatusCode": 204
      },
      {
        "Type": "Microsoft.AspNetCore.Mvc.ProblemDetails",
        "MediaTypes": [
          "text/plain",
          "application/json",
          "text/json"
        ],
        "StatusCode": 400
      },
      {
        "Type": "Microsoft.AspNetCore.Mvc.ProblemDetails",
        "MediaTypes": [
          "text/plain",
          "application/json",
          "text/json"
        ],
        "StatusCode": 401
      },
      {
        "Type": "Microsoft.AspNetCore.Mvc.ProblemDetails",
        "MediaTypes": [
          "text/plain",
          "application/json",
          "text/json"
        ],
        "StatusCode": 403
      },
      {
        "Type": "Microsoft.AspNetCore.Mvc.ProblemDetails",
        "MediaTypes": [
          "text/plain",
          "application/json",
          "text/json"
        ],
        "StatusCode": 404
      },
      {
        "Type": "System.Void",
        "MediaTypes": [],
        "StatusCode": 500
      }
    ]
  },
  {
    "ContainingType": "WMS.API.Controllers.V1.TenantsController",
    "Method": "CreateTenant",
    "RelativePath": "api/v1/Tenants",
    "HttpMethod": "POST",
    "IsController": true,
    "Order": 0,
    "Parameters": [
      {
        "Name": "command",
        "Type": "WMS.Application.Features.Tenants.Commands.CreateTenantCommand",
        "IsRequired": true
      }
    ],
    "ReturnTypes": [
      {
        "Type": "System.Object",
        "MediaTypes": [
          "text/plain",
          "application/json",
          "text/json"
        ],
        "StatusCode": 201
      },
      {
        "Type": "Microsoft.AspNetCore.Mvc.ProblemDetails",
        "MediaTypes": [
          "text/plain",
          "application/json",
          "text/json"
        ],
        "StatusCode": 400
      },
      {
        "Type": "System.Void",
        "MediaTypes": [],
        "StatusCode": 500
      }
    ]
  },
  {
    "ContainingType": "WMS.API.Controllers.V1.UsersController",
    "Method": "AssignRole",
    "RelativePath": "api/v1/Users/{userId}/roles",
    "HttpMethod": "POST",
    "IsController": true,
    "Order": 0,
    "Parameters": [
      {
        "Name": "userId",
        "Type": "System.Int32",
        "IsRequired": true
      },
      {
        "Name": "dto",
        "Type": "WMS.Application.Features.Users.Commands.AssignRoleDto",
        "IsRequired": true
      }
    ],
    "ReturnTypes": [
      {
        "Type": "System.Void",
        "MediaTypes": [],
        "StatusCode": 204
      },
      {
        "Type": "Microsoft.AspNetCore.Mvc.ProblemDetails",
        "MediaTypes": [
          "text/plain",
          "application/json",
          "text/json"
        ],
        "StatusCode": 400
      },
      {
        "Type": "Microsoft.AspNetCore.Mvc.ProblemDetails",
        "MediaTypes": [
          "text/plain",
          "application/json",
          "text/json"
        ],
        "StatusCode": 401
      },
      {
        "Type": "Microsoft.AspNetCore.Mvc.ProblemDetails",
        "MediaTypes": [
          "text/plain",
          "application/json",
          "text/json"
        ],
        "StatusCode": 404
      },
      {
        "Type": "System.Void",
        "MediaTypes": [],
        "StatusCode": 500
      }
    ]
  },
  {
    "ContainingType": "WMS.API.Controllers.V1.UsersController",
    "Method": "AssignUserToTenant",
    "RelativePath": "api/v1/Users/{userId}/tenant",
    "HttpMethod": "PUT",
    "IsController": true,
    "Order": 0,
    "Parameters": [
      {
        "Name": "userId",
        "Type": "System.Int32",
        "IsRequired": true
      },
      {
        "Name": "dto",
        "Type": "WMS.Application.Features.Users.Commands.AssignUserToTenantDto",
        "IsRequired": true
      }
    ],
    "ReturnTypes": [
      {
        "Type": "System.Void",
        "MediaTypes": [],
        "StatusCode": 204
      },
      {
        "Type": "Microsoft.AspNetCore.Mvc.ProblemDetails",
        "MediaTypes": [
          "text/plain",
          "application/json",
          "text/json"
        ],
        "StatusCode": 403
      },
      {
        "Type": "Microsoft.AspNetCore.Mvc.ProblemDetails",
        "MediaTypes": [
          "text/plain",
          "application/json",
          "text/json"
        ],
        "StatusCode": 404
      }
    ]
  },
  {
    "ContainingType": "WMS.API.Controllers.V1.UsersController",
    "Method": "GetMe",
    "RelativePath": "api/v1/Users/me",
    "HttpMethod": "GET",
    "IsController": true,
    "Order": 0,
    "Parameters": [],
    "ReturnTypes": [
      {
        "Type": "WMS.Application.Features.Users.Queries.CurrentUserDto",
        "MediaTypes": [
          "text/plain",
          "application/json",
          "text/json"
        ],
        "StatusCode": 200
      },
      {
        "Type": "Microsoft.AspNetCore.Mvc.ProblemDetails",
        "MediaTypes": [
          "text/plain",
          "application/json",
          "text/json"
        ],
        "StatusCode": 401
      },
      {
        "Type": "System.Void",
        "MediaTypes": [],
        "StatusCode": 500
      }
    ]
  },
  {
    "ContainingType": "WMS.API.Controllers.V1.WarehousesController",
    "Method": "CreateWarehouse",
    "RelativePath": "api/v1/Warehouses",
    "HttpMethod": "POST",
    "IsController": true,
    "Order": 0,
    "Parameters": [
      {
        "Name": "command",
        "Type": "WMS.Application.Features.Warehouses.Commands.CreateWarehouseCommand",
        "IsRequired": true
      }
    ],
    "ReturnTypes": [
      {
        "Type": "System.Object",
        "MediaTypes": [
          "text/plain",
          "application/json",
          "text/json"
        ],
        "StatusCode": 201
      },
      {
        "Type": "Microsoft.AspNetCore.Mvc.ProblemDetails",
        "MediaTypes": [
          "text/plain",
          "application/json",
          "text/json"
        ],
        "StatusCode": 400
      },
      {
        "Type": "System.Void",
        "MediaTypes": [],
        "StatusCode": 500
      }
    ]
  },
  {
    "ContainingType": "WMS.API.Controllers.V1.WarehousesController",
    "Method": "GetWarehouses",
    "RelativePath": "api/v1/Warehouses",
    "HttpMethod": "GET",
    "IsController": true,
    "Order": 0,
    "Parameters": [
      {
        "Name": "PageNumber",
        "Type": "System.Int32",
        "IsRequired": false
      },
      {
        "Name": "PageSize",
        "Type": "System.Int32",
        "IsRequired": false
      }
    ],
    "ReturnTypes": [
      {
        "Type": "WMS.Application.Common.Models.PagedResult\u00601[[WMS.Application.Features.Warehouses.Queries.WarehouseListDto, WMS.Application, Version=1.0.0.0, Culture=neutral, PublicKeyToken=null]]",
        "MediaTypes": [
          "text/plain",
          "application/json",
          "text/json"
        ],
        "StatusCode": 200
      },
      {
        "Type": "Microsoft.AspNetCore.Mvc.ProblemDetails",
        "MediaTypes": [
          "text/plain",
          "application/json",
          "text/json"
        ],
        "StatusCode": 400
      },
      {
        "Type": "Microsoft.AspNetCore.Mvc.ProblemDetails",
        "MediaTypes": [
          "text/plain",
          "application/json",
          "text/json"
        ],
        "StatusCode": 401
      },
      {
        "Type": "Microsoft.AspNetCore.Mvc.ProblemDetails",
        "MediaTypes": [
          "text/plain",
          "application/json",
          "text/json"
        ],
        "StatusCode": 404
      },
      {
        "Type": "System.Void",
        "MediaTypes": [],
        "StatusCode": 500
      }
    ]
  },
  {
    "ContainingType": "WMS.API.Controllers.V1.WarehousesController",
    "Method": "GetWarehouseById",
    "RelativePath": "api/v1/Warehouses/{id}",
    "HttpMethod": "GET",
    "IsController": true,
    "Order": 0,
    "Parameters": [
      {
        "Name": "id",
        "Type": "System.Int32",
        "IsRequired": true
      }
    ],
    "ReturnTypes": [
      {
        "Type": "WMS.Application.Features.Warehouses.Queries.WarehouseDto",
        "MediaTypes": [
          "text/plain",
          "application/json",
          "text/json"
        ],
        "StatusCode": 200
      },
      {
        "Type": "Microsoft.AspNetCore.Mvc.ProblemDetails",
        "MediaTypes": [
          "text/plain",
          "application/json",
          "text/json"
        ],
        "StatusCode": 404
      },
      {
        "Type": "System.Void",
        "MediaTypes": [],
        "StatusCode": 500
      }
    ]
  },
  {
    "ContainingType": "WMS.API.Controllers.V1.WarehousesController",
    "Method": "UpdateWarehouse",
    "RelativePath": "api/v1/Warehouses/{id}",
    "HttpMethod": "PUT",
    "IsController": true,
    "Order": 0,
    "Parameters": [
      {
        "Name": "id",
        "Type": "System.Int32",
        "IsRequired": true
      },
      {
        "Name": "command",
        "Type": "WMS.Application.Features.Warehouses.Commands.UpdateWarehouseCommand",
        "IsRequired": true
      }
    ],
    "ReturnTypes": [
      {
        "Type": "System.Void",
        "MediaTypes": [],
        "StatusCode": 204
      },
      {
        "Type": "Microsoft.AspNetCore.Mvc.ProblemDetails",
        "MediaTypes": [
          "text/plain",
          "application/json",
          "text/json"
        ],
        "StatusCode": 400
      },
      {
        "Type": "Microsoft.AspNetCore.Mvc.ProblemDetails",
        "MediaTypes": [
          "text/plain",
          "application/json",
          "text/json"
        ],
        "StatusCode": 404
      },
      {
        "Type": "System.Void",
        "MediaTypes": [],
        "StatusCode": 500
      }
    ]
  },
  {
    "ContainingType": "WMS.API.Controllers.V1.WarehousesController",
    "Method": "DeactivateWarehouse",
    "RelativePath": "api/v1/Warehouses/{id}/deactivate",
    "HttpMethod": "POST",
    "IsController": true,
    "Order": 0,
    "Parameters": [
      {
        "Name": "id",
        "Type": "System.Int32",
        "IsRequired": true
      }
    ],
    "ReturnTypes": [
      {
        "Type": "System.Void",
        "MediaTypes": [],
        "StatusCode": 204
      },
      {
        "Type": "Microsoft.AspNetCore.Mvc.ProblemDetails",
        "MediaTypes": [
          "text/plain",
          "application/json",
          "text/json"
        ],
        "StatusCode": 400
      },
      {
        "Type": "Microsoft.AspNetCore.Mvc.ProblemDetails",
        "MediaTypes": [
          "text/plain",
          "application/json",
          "text/json"
        ],
        "StatusCode": 401
      },
      {
        "Type": "Microsoft.AspNetCore.Mvc.ProblemDetails",
        "MediaTypes": [
          "text/plain",
          "application/json",
          "text/json"
        ],
        "StatusCode": 403
      },
      {
        "Type": "Microsoft.AspNetCore.Mvc.ProblemDetails",
        "MediaTypes": [
          "text/plain",
          "application/json",
          "text/json"
        ],
        "StatusCode": 404
      },
      {
        "Type": "System.Void",
        "MediaTypes": [],
        "StatusCode": 500
      }
    ]
  }
]